mogptk/__init__.py
mogptk/bnse.py
mogptk/conv.py
mogptk/csm.py
mogptk/data.py
mogptk/dataset.py
mogptk/errors.py
mogptk/init.py
mogptk/model.py
mogptk/mosm.py
mogptk/plot.py
mogptk/serie.py
mogptk/sm.py
mogptk/sm_lmc.py
mogptk/transformer.py
mogptk/util.py
mogptk/gpr/__init__.py
mogptk/gpr/config.py
mogptk/gpr/distribution.py
mogptk/gpr/kernel.py
mogptk/gpr/likelihood.py
mogptk/gpr/mean.py
mogptk/gpr/model.py
mogptk/gpr/multioutput.py
mogptk/gpr/parameter.py
mogptk/gpr/plot.py
mogptk/gpr/singleoutput.py
mogptk/gpr/util.py
mogptk/kernels/__init__.py
mogptk/kernels/config.py
mogptk/kernels/conv.py
mogptk/kernels/csm.py
mogptk/kernels/kernel.py
mogptk/kernels/mean.py
mogptk/kernels/model.py
mogptk/kernels/mosm.py
mogptk/kernels/multikernel.py
mogptk/kernels/multioutput.py
mogptk/kernels/noise.py
mogptk/kernels/parameter.py
mogptk/kernels/singleoutput.py
mogptk/kernels/sm.py
mogptk/kernels/sm_lmc.py
mogptk/kernels/util.py
mogptk/models/__init__.py
mogptk/models/conv.py
mogptk/models/csm.py
mogptk/models/mohsm.py
mogptk/models/mosm.py
mogptk/models/sm.py
mogptk/models/sm_lmc.py
mogptk-0.5.2.dist-info/LICENSE
mogptk-0.5.2.dist-info/METADATA
mogptk-0.5.2.dist-info/WHEEL
mogptk-0.5.2.dist-info/top_level.txt
mogptk-0.5.2.dist-info/RECORD
