Metadata-Version: 2.1
Name: mogptk
Version: 0.5.2
Summary: Multi-Output Gaussian Process ToolKit
Home-page: https://github.com/GAMES-UChile/mogptk
Author: Taco de Wolff, Alejandro Cuevas, Felipe Tobar
Author-email: tacodewolff@gmail.com
License: MIT
Keywords: MOGP,MOSM,GP,Gaussian Process,Multi-Output,Tobar,Parra
Requires-Python: >=3.6
License-File: LICENSE
Requires-Dist: matplotlib >=3.3
Requires-Dist: numpy >=1.10
Requires-Dist: pandas
Requires-Dist: python-dateutil
Requires-Dist: scipy >=1.7
Requires-Dist: torch >=1.11
Requires-Dist: ipython
